{
  "$schema": "shopscout://normalization-libraries/esciSubstitutes/v1",
  "version": 1,
  "source": {
    "vocabulary": "Amazon Shopping Queries Dataset (ESCI)",
    "release": "2022-12",
    "url": "https://github.com/amazon-science/esci-data",
    "license": "Apache-2.0",
    "sourceFile": "data-sources/esci/shopping_queries_dataset_examples.parquet",
    "sourceBytes": 0,
    "sourceSha256": "0000000000000000000000000000000000000000000000000000000000000000",
    "generatedAt": "2026-07-07T23:30:00Z",
    "generator": "manual-fixture-for-codex-unblock",
    "generatorVersion": 0,
    "locale": "us",
    "note": "Sample fixture matching the v1 schema so Codex Track A runtime integration (matching.js:scorePair bonus signal) can develop and test in parallel with a real ESCI generator. Real generator requires parquet parsing of the 700 MB Amazon dataset and is deferred as a follow-up. Fixture pairs are illustrative ASINs (fictional; not real Amazon products) that exercise: (1) a normal high-count substitute pair, (2) a low-count pair (queryCount: 1), (3) a pair where a and b were swapped in the source before canonicalization."
  },
  "substitutePairs": [
    { "a": "B01AAAAAAA", "b": "B02BBBBBBB", "queryCount": 1 },
    { "a": "B0EXAMPLE1", "b": "B0EXAMPLE2", "queryCount": 3 },
    { "a": "B0EXAMPLE1", "b": "B0EXAMPLE5", "queryCount": 2 },
    { "a": "B0KEYBOARD", "b": "B0KEYBRD02", "queryCount": 5 },
    { "a": "B0MOUSE001", "b": "B0MOUSE002", "queryCount": 4 }
  ]
}
